{"cameraMode":{"drawMode":0,"name":"Shaded","section":"Shading Mode"},"sceneLighting":false,"audioPlay":false,"sceneViewState":{"showFog":true,"showMaterialUpdate":false,"showSkybox":false,"showFlares":true,"showImageEffects":true,"showParticleSystems":true},"in2DMode":false,"pivot":{"x":1.600000023841858,"y":4.722111225128174,"z":3.789978504180908},"rotation":{"x":0.09516934305429459,"y":-0.8941015601158142,"z":0.22767727077007295,"w":0.37408488988876345},"size":4.912676811218262,"orthographic":false}