{"cameraMode":{"drawMode":0,"name":"Shaded","section":"Shading Mode"},"sceneLighting":false,"audioPlay":false,"sceneViewState":{"showFog":true,"showMaterialUpdate":false,"showSkybox":false,"showFlares":true,"showImageEffects":true,"showParticleSystems":true},"in2DMode":false,"pivot":{"x":20.23676109313965,"y":-1.5672030448913575,"z":-10.624813079833985},"rotation":{"x":0.04394158348441124,"y":-0.9529547691345215,"z":0.16898176074028016,"w":0.24779821932315827},"size":7.19447660446167,"orthographic":false}